infi.storagemodel-0.4.32-py3.7-nspkg.pth
infi/storagemodel/__init__.py
infi/storagemodel/__version__.py
infi/storagemodel/errors.py
infi/storagemodel/aix/__init__.py
infi/storagemodel/aix/mount.py
infi/storagemodel/aix/native_multipath.py
infi/storagemodel/aix/rescan.py
infi/storagemodel/aix/scsi.py
infi/storagemodel/base/__init__.py
infi/storagemodel/base/diagnostic.py
infi/storagemodel/base/disk.py
infi/storagemodel/base/filesystem.py
infi/storagemodel/base/gevent_wrapper.py
infi/storagemodel/base/inquiry.py
infi/storagemodel/base/mount.py
infi/storagemodel/base/multipath.py
infi/storagemodel/base/partition.py
infi/storagemodel/base/scsi.py
infi/storagemodel/base/utils.py
infi/storagemodel/connectivity/__init__.py
infi/storagemodel/connectivity/tests.py
infi/storagemodel/examples/__init__.py
infi/storagemodel/examples/tests.py
infi/storagemodel/linux/__init__.py
infi/storagemodel/linux/block.py
infi/storagemodel/linux/disk.py
infi/storagemodel/linux/filesystem.py
infi/storagemodel/linux/iscsi.py
infi/storagemodel/linux/mount.py
infi/storagemodel/linux/native_multipath.py
infi/storagemodel/linux/partition.py
infi/storagemodel/linux/scsi.py
infi/storagemodel/linux/sysfs.py
infi/storagemodel/linux/veritas_multipath.py
infi/storagemodel/linux/rescan_scsi_bus/__init__.py
infi/storagemodel/linux/rescan_scsi_bus/getters.py
infi/storagemodel/linux/rescan_scsi_bus/logic.py
infi/storagemodel/linux/rescan_scsi_bus/scsi.py
infi/storagemodel/linux/rescan_scsi_bus/utils.py
infi/storagemodel/linux/rescan_scsi_bus/tests/__init__.py
infi/storagemodel/osx/__init__.py
infi/storagemodel/predicates/__init__.py
infi/storagemodel/predicates/tests.py
infi/storagemodel/solaris/__init__.py
infi/storagemodel/solaris/filesystem.py
infi/storagemodel/solaris/mount.py
infi/storagemodel/solaris/native_multipath.py
infi/storagemodel/solaris/scsi.py
infi/storagemodel/solaris/veritas_multipath.py
infi/storagemodel/solaris/devicemanager/__init__.py
infi/storagemodel/solaris/devicemanager/kstat.py
infi.storagemodel-0.4.32.dist-info/LICENSE
infi.storagemodel-0.4.32.dist-info/LICENSE.txt
infi.storagemodel-0.4.32.dist-info/METADATA
infi.storagemodel-0.4.32.dist-info/WHEEL
infi.storagemodel-0.4.32.dist-info/entry_points.txt
infi.storagemodel-0.4.32.dist-info/namespace_packages.txt
infi.storagemodel-0.4.32.dist-info/top_level.txt
infi.storagemodel-0.4.32.dist-info/RECORD
