Metadata-Version: 2.1
Name: infi.storagemodel
Version: 0.4.32
Summary: A high-level library for traversing the OS storage model.
Home-page: https://github.com/Infinidat/infi.storagemodel
Author: Arnon Yaari
Author-email: arnony@infinidat.com
License: BSD
Platform: UNKNOWN
Classifier: Intended Audience :: Developers
Classifier: Intended Audience :: System Administrators
Classifier: License :: OSI Approved :: BSD License
Classifier: Operating System :: OS Independent
Classifier: Programming Language :: Python
Classifier: Programming Language :: Python :: 2
Classifier: Programming Language :: Python :: 3
Classifier: Topic :: Software Development :: Libraries :: Python Modules
Requires-Dist: distro
Requires-Dist: infi.asi
Requires-Dist: infi.blocking
Requires-Dist: infi.cwrap
Requires-Dist: infi.devicemanager
Requires-Dist: infi.diskmanagement
Requires-Dist: infi.dtypes.hctl
Requires-Dist: infi.dtypes.iqn
Requires-Dist: infi.dtypes.wwn
Requires-Dist: infi.exceptools
Requires-Dist: infi.hbaapi
Requires-Dist: infi.instruct
Requires-Dist: infi.iscsiapi
Requires-Dist: infi.mount-utils
Requires-Dist: infi.multipathtools
Requires-Dist: infi.os-info
Requires-Dist: infi.parted
Requires-Dist: infi.pyutils
Requires-Dist: infi.sgutils
Requires-Dist: infi.traceback
Requires-Dist: infi.wioctl
Requires-Dist: infi.wmpio
Requires-Dist: setuptools
Requires-Dist: six
